dj_pg_access_control/__init__.py
dj_pg_access_control/context_managers.py
dj_pg_access_control/utils.py
django_postgres_access_control-0.2.dist-info/LICENSE
django_postgres_access_control-0.2.dist-info/METADATA
django_postgres_access_control-0.2.dist-info/WHEEL
django_postgres_access_control-0.2.dist-info/top_level.txt
django_postgres_access_control-0.2.dist-info/RECORD
