Metadata-Version: 2.1
Name: django-postgres-access-control
Version: 0.2
Summary: Access control for Django projects using PostgreSQL
Home-page: https://github.com/eeriksp/django_postgres_access_control
Author: Eerik Sven Puudist
License: UNKNOWN
Project-URL: Bug Tracker, https://github.com/django-access-control/django-access-control/issue://github.com/eeriksp/django_postgres_access_control
Platform: UNKNOWN
Classifier: Programming Language :: Python :: 3
Classifier: License :: OSI Approved :: MIT License
Classifier: Operating System :: OS Independent
Requires-Python: >=3.8
License-File: LICENSE
Requires-Dist: django
